terre/__init__.py
terre-0.1.dist-info/DESCRIPTION.rst
terre-0.1.dist-info/METADATA
terre-0.1.dist-info/RECORD
terre-0.1.dist-info/WHEEL
terre-0.1.dist-info/metadata.json
terre-0.1.dist-info/top_level.txt
