Metadata-Version: 2.0
Name: terre
Version: 0.1
Summary: A low-level system programming language embedded in Python
Home-page: https://github.com/leonardt/terre
Author: Leonard Truong
Author-email: lenny@cs.stanford.edu
License: BSD License
Platform: UNKNOWN
Requires-Python: >=3.6
